README.rst
pyproject.toml
setup.py
pricefetch/__init__.py
pricefetch/blackandscholes.py
pricefetch/constants.py
pricefetch/pricefetch.py
pricefetch.egg-info/PKG-INFO
pricefetch.egg-info/SOURCES.txt
pricefetch.egg-info/dependency_links.txt
pricefetch.egg-info/requires.txt
pricefetch.egg-info/top_level.txt