Metadata-Version: 2.1
Name: pricefetch
Version: 0.1.1
Summary: Tool for fetching realtime options and stock data
Home-page: UNKNOWN
Author: Devesh Todarwal, Rutuvi Narang
Author-email: todarwal.devesh@gmail.com, rutuvinarang@gmail.com
License: MIT
Keywords: stocks options finance market shares greeks implied volatility real-time googlefinance yahoofinance
Platform: UNKNOWN
Classifier: Development Status :: 4 - Beta
Classifier: Intended Audience :: Financial and Insurance Industry
Classifier: Intended Audience :: Education
Classifier: Topic :: Software Development :: Libraries :: Python Modules
Classifier: License :: OSI Approved :: MIT License
Classifier: Programming Language :: Python :: 3
Classifier: Programming Language :: Python :: 3.5
